{
    "fluentMethods": true,
    "relationships": [
        {
            "relationshipType": "one-to-many",
            "relationshipName": "trabajador",
            "otherEntityName": "trabajador",
            "otherEntityRelationshipName": "cartrab"
        }
    ],
    "fields": [
        {
            "fieldName": "vDesCartra",
            "fieldType": "String",
            "fieldValidateRules": [
                "required",
                "maxlength"
            ],
            "fieldValidateRulesMaxlength": 100
        },
        {
            "fieldName": "nUsuareg",
            "fieldType": "Integer",
            "fieldValidateRules": [
                "required"
            ]
        },
        {
            "fieldName": "tFecreg",
            "fieldType": "Instant",
            "fieldValidateRules": [
                "required"
            ]
        },
        {
            "fieldName": "nFlgactivo",
            "fieldType": "Boolean",
            "fieldValidateRules": [
                "required"
            ]
        },
        {
            "fieldName": "nSedereg",
            "fieldType": "Integer",
            "fieldValidateRules": [
                "required"
            ]
        },
        {
            "fieldName": "nUsuaupd",
            "fieldType": "Integer"
        },
        {
            "fieldName": "tFecupd",
            "fieldType": "Instant"
        },
        {
            "fieldName": "nSedeupd",
            "fieldType": "Integer"
        }
    ],
    "changelogDate": "20171122172607",
    "entityTableName": "cartrab",
    "dto": "no",
    "pagination": "no",
    "service": "no",
    "jpaMetamodelFiltering": false,
    "microserviceName": "consultas"
}